jepa/__init__.py
jepa/py.typed
jepa/cli/__init__.py
jepa/cli/__main__.py
jepa/cli/evaluate.py
jepa/cli/train.py
jepa/cli/utils.py
jepa/config/__init__.py
jepa/config/config.py
jepa/config/default_config.yaml
jepa/config/nlp_config.yaml
jepa/config/timeseries_config.yaml
jepa/config/vision_config.yaml
jepa/data/__init__.py
jepa/data/dataset.py
jepa/data/hf_compatibility.py
jepa/data/transforms.py
jepa/data/utils.py
jepa/loggers/__init__.py
jepa/loggers/base_logger.py
jepa/loggers/console_logger.py
jepa/loggers/multi_logger.py
jepa/loggers/tensorboard_logger.py
jepa/loggers/wandb_logger.py
jepa/loss_functions/__init__.py
jepa/loss_functions/loss_functions.py
jepa/models/__init__.py
jepa/models/base.py
jepa/models/encoder.py
jepa/models/jepa.py
jepa/models/predictor.py
jepa/trainer/__init__.py
jepa/trainer/eval.py
jepa/trainer/trainer.py
jepa/trainer/utils.py
jepa-0.1.4.dist-info/licenses/LICENSE
jepa-0.1.4.dist-info/METADATA
jepa-0.1.4.dist-info/WHEEL
jepa-0.1.4.dist-info/entry_points.txt
jepa-0.1.4.dist-info/top_level.txt
jepa-0.1.4.dist-info/RECORD
